mags_hypermodern_python/__init__.py
mags_hypermodern_python/console.py
mags_hypermodern_python/wikipedia.py
mags_hypermodern_python-0.1.0.dist-info/entry_points.txt
mags_hypermodern_python-0.1.0.dist-info/LICENSE
mags_hypermodern_python-0.1.0.dist-info/WHEEL
mags_hypermodern_python-0.1.0.dist-info/METADATA
mags_hypermodern_python-0.1.0.dist-info/RECORD
